formulatoolkit/__init__.py
tests/__init__.py
tests/test_dependency_resolver.py
tests/test_expression_parser.py
formulatoolkit-0.0.2.dist-info/METADATA
formulatoolkit-0.0.2.dist-info/WHEEL
formulatoolkit-0.0.2.dist-info/top_level.txt
formulatoolkit-0.0.2.dist-info/RECORD
