Metadata-Version: 2.1
Name: formulatoolkit
Version: 0.0.2
Summary: Formula toolkit ( pure python code )
Home-page: https://github.com/ozw1z5rd/py-expression-eval.git
Author: Alessio Palma
Author-email: ozw1z5rd@gmail.com
License: UNKNOWN
Platform: UNKNOWN
Classifier: Programming Language :: Python :: 3
Classifier: License :: OSI Approved :: MIT License
Classifier: Operating System :: OS Independent
Requires-Python: >=2.7
